lepton/controller.py
lepton/domain.py
lepton/emitter.pyd
lepton/group.pyd
lepton/particle_struct.py
lepton/pygame_renderer.py
lepton/renderer.pyd
lepton/system.py
lepton/texturizer.py
lepton/_controller.pyd
lepton/_domain.pyd
lepton/_texturizer.pyd
lepton/__init__.py
lepton/examples/bouncy.py
lepton/examples/bubble.png
lepton/examples/fire.py
lepton/examples/fireworks.py
lepton/examples/flare1.png
lepton/examples/flare2.png
lepton/examples/flare3.png
lepton/examples/flare4.png
lepton/examples/flare5.png
lepton/examples/flyby.py
lepton/examples/generate.py
lepton/examples/letters.py
lepton/examples/logo.py
lepton/examples/magnet.py
lepton/examples/Particle.bmp
lepton/examples/puff.png
lepton/examples/pygame_bubble.py
lepton/examples/pygame_fill.py
lepton/examples/smoke.py
lepton/examples/splode.py
lepton/examples/splode2d.py
lepton/examples/tunnel.py
lepton/examples/vortex.py
lepton/examples/__init__.py
lepton/examples/logo_frames/logo0.png
lepton/examples/logo_frames/logo1.png
lepton/examples/logo_frames/logo2.png
lepton/examples/logo_frames/logo3.png
lepton/examples/logo_frames/logo4.png
lepton/examples/logo_frames/logo5.png
lepton/examples/logo_frames/logo6.png
wasabi_lepton-1.0b2.dist-info/DESCRIPTION.rst
wasabi_lepton-1.0b2.dist-info/METADATA
wasabi_lepton-1.0b2.dist-info/metadata.json
wasabi_lepton-1.0b2.dist-info/RECORD
wasabi_lepton-1.0b2.dist-info/top_level.txt
wasabi_lepton-1.0b2.dist-info/WHEEL
