Metadata-Version: 2.0
Name: wasabi-lepton
Version: 1.0b2
Summary: Wasabi-Lepton: A fork of Lepton, A high-performance, pluggable particle engine and API for Python
Home-page: http://code.google.com/p/py-lepton/
Author: Casey Duncan, Harry Tormey & Contributors
Author-email: py-lepton-users@googlegroups.com
License: MIT
Platform: UNKNOWN
Classifier: Development Status :: 4 - Beta
Classifier: Topic :: Multimedia :: Graphics
Classifier: License :: OSI Approved :: MIT License
Classifier: Intended Audience :: Developers
Classifier: Operating System :: MacOS :: MacOS X
Classifier: Operating System :: Microsoft :: Windows
Classifier: Operating System :: POSIX
